meta_optimize/__init__.py
meta_optimize/meta_optimize_api.py
meta_optimize/optimizer_performance.py
meta_optimize/test_functions.py
meta_optimize-0.0.1.dist-info/LICENSE
meta_optimize-0.0.1.dist-info/METADATA
meta_optimize-0.0.1.dist-info/WHEEL
meta_optimize-0.0.1.dist-info/top_level.txt
meta_optimize-0.0.1.dist-info/RECORD
